MANIFEST.in
README.md
setup.py
src/masonite/errors/Handler.py
src/masonite/errors/SolutionsIntegration.py
src/masonite/errors/StackOverflowIntegration.py
src/masonite/errors/__init__.py
src/masonite/errors/providers/ErrorProvider.py
src/masonite/errors/providers/__init__.py
src/masonite/errors/templates/__init__.py
src/masonite/errors/templates/exception.html
src/masonite/errors/templates/solutions.html
src/masonite/errors/templates/stackoverflow.html
src/masonite/errors/templates/css/prism.css
src/masonite/errors/templates/css/tailwind.css
src/masonite_errors.egg-info/PKG-INFO
src/masonite_errors.egg-info/SOURCES.txt
src/masonite_errors.egg-info/dependency_links.txt
src/masonite_errors.egg-info/requires.txt
src/masonite_errors.egg-info/top_level.txt